[
  {
    "id": "toeic-part5-advanced-grammar-strategy",
    "title": "TOEIC Part5特定文法問題の秒殺テク！仮定法・倒置攻略",
    "description": "TOEIC Part5で仮定法や倒置など、特定の文法問題に苦戦していませんか？この記事では、難解な文法項目をピンポイントで攻略するテクニックと練習法を解説。得点アップに直結します！"
  },
  {
    "id": "business-english-email-nuance-phrases-request-refusal",
    "title": "英語ビジネスメールで誤解されない！催促・断りの絶妙表現",
    "description": "英語でのビジネスメール、催促や断りの伝え方に困っていませんか？この記事では、相手に失礼なく意図を正確に伝えるための具体的な英語フレーズと、微妙なニュアンスの出し方を解説します。"
  },
  {
    "id": "english-conference-call-listening-difficulty-phrases",
    "title": "英語電話会議で聞き取れない時の神フレーズ！焦らず対応",
    "description": "英語の電話会議で「聞き取れない…」と焦る経験はありませんか？この記事では、相手に失礼なく聞き返すための具体的な英語フレーズや、聞き取り精度を上げるための事前準備を紹介します。"
  },
  {
    "id": "english-learning-app-pronunciation-vocabulary-comparison",
    "title": "英語学習アプリ特定機能比較！発音矯正/単語暗記特化型",
    "description": "数ある英語学習アプリ、どれを選べばいいか迷いますよね。この記事では「発音矯正」や「スキマ時間での単語暗記」など、特定の目的に特化したアプリを徹底比較！あなたに最適なアプリが見つかります。"
  },
  {
    "id": "netflix-shadowing-beginners-guide-drama-selection",
    "title": "初心者向けNetflixシャドーイング！挫折しないドラマと方法",
    "description": "海外ドラマで楽しくシャドーイングしたいけど、難しくて挫折しそう…そんな初心者の方へ。この記事では、無理なく続けられる具体的なシャドーイング方法と、初心者におすすめのNetfixドラマを紹介します！"
  },
  {
    "id": "english-presentation-opening-hooks-audience-engagement",
    "title": "英語プレゼン冒頭で掴む！聴衆を惹きつける導入テクニック",
    "description": "英語でのプレゼンテーション、最初の数分で聴衆の心を掴めていますか？この記事では、聴衆を惹きつける効果的な導入テクニックや、すぐに使える英語フレーズを具体例と共に紹介します。"
  },
  {
    "id": "english-small-talk-questions-avoid-awkward-silence",
    "title": "英語雑談で話題が途切れない！ネイティブ流質問テクニック",
    "description": "英語でのスモールトーク、ネタ切れで気まずい沈黙に悩んでいませんか？この記事では、会話が自然に続くネイティブ流の質問テクニックや、鉄板の話題集を紹介。もう雑談は怖くありません！"
  },
  {
    "id": "toeic-listening-part2-indirect-answers-strategy",
    "title": "TOEIC Part2変化球応答も怖くない！間接的回答攻略法",
    "description": "TOEICリスニングPart2で「え、これが正解？」と戸惑う変化球の応答。この記事では、間接的な応答パターンを徹底分析し、具体的な攻略法と練習問題を伝授。確実にスコアアップを目指します。"
  },
  {
    "id": "english-diary-writing-tips-consistency-topic-ideas",
    "title": "英語日記が続く！初心者向けネタ出しと書き方3ステップ",
    "description": "英語力アップに効果的な英語日記。でも「何を書けば…」と三日坊主に？この記事では、初心者でも楽しく続けられる具体的な書き方ステップと、豊富なネタ出しのヒント、便利なフレーズを紹介します。"
  },
  {
    "id": "online-english-meeting-speaking-timing-interruption-phrases",
    "title": "英語オンライン会議で発言する勇気！スマートな割込み術",
    "description": "英語でのオンライン会議、発言のタイミングが掴めず黙り込んでいませんか？この記事では、スマートに会話に入り込むための具体的な英語フレーズと、発言の機会を逃さないためのコツを解説します。"
  }
]